collective.sendinblue-2.0.4-py3.12-nspkg.pth
collective/sendinblue/__init__.py
collective/sendinblue/configure.zcml
collective/sendinblue/interfaces.py
collective/sendinblue/sendinblue.py
collective/sendinblue/setuphandlers.py
collective/sendinblue/testing.py
collective/sendinblue/upgrades.py
collective/sendinblue/vocabularies.py
collective/sendinblue/browser/__init__.py
collective/sendinblue/browser/configure.zcml
collective/sendinblue/browser/controlpanel.pt
collective/sendinblue/browser/controlpanel.py
collective/sendinblue/browser/portlet.pt
collective/sendinblue/browser/portlet.py
collective/sendinblue/browser/redirection_portlet.pt
collective/sendinblue/browser/redirection_portlet.py
collective/sendinblue/browser/images/sendinblue.png
collective/sendinblue/browser/stylesheets/sendinblue.css
collective/sendinblue/locales/collective.sendinblue.pot
collective/sendinblue/locales/update.sh
collective/sendinblue/locales/en/LC_MESSAGES/collective.sendinblue.po
collective/sendinblue/locales/es/LC_MESSAGES/collective.sendinblue.po
collective/sendinblue/locales/fr/LC_MESSAGES/collective.sendinblue.po
collective/sendinblue/profiles/default/browserlayer.xml
collective/sendinblue/profiles/default/controlpanel.xml
collective/sendinblue/profiles/default/metadata.xml
collective/sendinblue/profiles/default/portlets.xml
collective/sendinblue/profiles/default/registry.xml
collective/sendinblue/profiles/uninstall/browserlayer.xml
collective/sendinblue/profiles/uninstall/controlpanel.xml
collective/sendinblue/profiles/uninstall/metadata.xml
collective/sendinblue/tests/__init__.py
collective/sendinblue/tests/test_setup.py
collective_sendinblue-2.0.4.dist-info/licenses/LICENSE.GPL
collective_sendinblue-2.0.4.dist-info/licenses/LICENSE.rst
collective_sendinblue-2.0.4.dist-info/METADATA
collective_sendinblue-2.0.4.dist-info/WHEEL
collective_sendinblue-2.0.4.dist-info/entry_points.txt
collective_sendinblue-2.0.4.dist-info/namespace_packages.txt
collective_sendinblue-2.0.4.dist-info/top_level.txt
collective_sendinblue-2.0.4.dist-info/RECORD
