Metadata-Version: 2.4
Name: collective.sendinblue
Version: 2.0.4
Summary: Sendinblue integration for Plone
Home-page: https://github.com/collective/collective.sendinblue
Author: Laurent Lasudry
Author-email: laurent.lasudry@affinitic.be
License: GPL version 2
Keywords: Python Plone
Classifier: Environment :: Web Environment
Classifier: Framework :: Plone
Classifier: Framework :: Plone :: 5.2
Classifier: Framework :: Plone :: 6.0
Classifier: Programming Language :: Python
Classifier: Programming Language :: Python :: 2.7
Classifier: Programming Language :: Python :: 3.7
Classifier: Programming Language :: Python :: 3.8
Classifier: Operating System :: OS Independent
Classifier: License :: OSI Approved :: GNU General Public License v2 (GPLv2)
License-File: LICENSE.GPL
License-File: LICENSE.rst
Requires-Dist: Products.GenericSetup>=1.8.2
Requires-Dist: plone.api
Requires-Dist: setuptools
Requires-Dist: sib-api-v3-sdk
Requires-Dist: plone.formwidget.recaptcha
Provides-Extra: test
Requires-Dist: plone.app.testing; extra == "test"
Requires-Dist: plone.testing>=5.0.0; extra == "test"
Requires-Dist: plone.app.contenttypes; extra == "test"
Requires-Dist: plone.app.robotframework[debug]; extra == "test"
Dynamic: author
Dynamic: author-email
Dynamic: classifier
Dynamic: description
Dynamic: home-page
Dynamic: keywords
Dynamic: license
Dynamic: license-file
Dynamic: provides-extra
Dynamic: requires-dist
Dynamic: summary
